webull/__init__.py
webull/endpoints.py
webull/streamconn.py
webull/webull.py
webull-0.0.9.dist-info/LICENSE
webull-0.0.9.dist-info/METADATA
webull-0.0.9.dist-info/WHEEL
webull-0.0.9.dist-info/top_level.txt
webull-0.0.9.dist-info/RECORD
